streamlit_google_picker/__init__.py
streamlit_google_picker/example.py
streamlit_google_picker/uploaded_file.py
streamlit_google_picker/frontend/build/bootstrap.min.css
streamlit_google_picker/frontend/build/index.html
streamlit_google_picker/frontend/build/assets/index-DSA5vz50.css
streamlit_google_picker/frontend/build/assets/index-Dz_Xofck.js
streamlit_google_picker-0.2.7.dist-info/licenses/LICENSE
streamlit_google_picker-0.2.7.dist-info/METADATA
streamlit_google_picker-0.2.7.dist-info/WHEEL
streamlit_google_picker-0.2.7.dist-info/top_level.txt
streamlit_google_picker-0.2.7.dist-info/RECORD
