Metadata-Version: 2.4
Name: streamlit-google-picker
Version: 0.2.7
Summary: Streamlit component for picking files from Google Drive
Author-email: Lounes Allioui <hello@lounesallioui.com>
Classifier: Programming Language :: Python :: 3
Classifier: Operating System :: OS Independent
Requires-Python: >=3.9
License-File: LICENSE
Requires-Dist: streamlit>=1.45.0
Provides-Extra: oauth
Requires-Dist: python-dotenv>=1.0.1; extra == "oauth"
Requires-Dist: streamlit-oauth>=0.1.14; extra == "oauth"
Provides-Extra: dev
Requires-Dist: pytest>=8.4.1; extra == "dev"
Requires-Dist: playwright>=1.53.0; extra == "dev"
Requires-Dist: setuptools>=80.9.0; extra == "dev"
Dynamic: license-file
